blackbolt/__init__.py
blackbolt/main.py
blackbolt/data/ML TS XAI HC/ML/requirements.txt
blackbolt/data/ML TS XAI HC/ML/ML 1/1. EDA-PCA (Balance Scale Dataset).ipynb
blackbolt/data/ML TS XAI HC/ML/ML 1/1. EDA-PCA (Rice Dataset).ipynb
blackbolt/data/ML TS XAI HC/ML/ML 1/10. HMM Veterbi.ipynb
blackbolt/data/ML TS XAI HC/ML/ML 1/2. KNN (Balance Scale Dataset).ipynb
blackbolt/data/ML TS XAI HC/ML/ML 1/2. KNN (Iris Dataset).ipynb
blackbolt/data/ML TS XAI HC/ML/ML 1/2. KNN (Sobar-72 Dataset).ipynb
blackbolt/data/ML TS XAI HC/ML/ML 1/3. LDA (Balance Scale Dataset).ipynb
blackbolt/data/ML TS XAI HC/ML/ML 1/3. LDA (NPHA Doctor Visits Dataset).ipynb
blackbolt/data/ML TS XAI HC/ML/ML 1/4. Linear Regression (Machine Dataset).ipynb
blackbolt/data/ML TS XAI HC/ML/ML 1/4. Linear Regression (Real Estate Dataset).ipynb
blackbolt/data/ML TS XAI HC/ML/ML 1/5. Logistic Regression (Magic04 Dataset).ipynb
blackbolt/data/ML TS XAI HC/ML/ML 1/5. Logistic Regression (Wine Dataset).ipynb
blackbolt/data/ML TS XAI HC/ML/ML 1/6. Naive Bayes Classifier (Agaricus Lepiota Dataset).ipynb
blackbolt/data/ML TS XAI HC/ML/ML 1/6. Naive Bayes Classifier (Wine Dataset).ipynb
blackbolt/data/ML TS XAI HC/ML/ML 1/7. SVM (Rice Dataset).ipynb
blackbolt/data/ML TS XAI HC/ML/ML 1/8. FeedForward NN (Sobar72 Dataset).ipynb
blackbolt/data/ML TS XAI HC/ML/ML 1/9. CNN (Cifar10 Dataset).ipynb
blackbolt/data/ML TS XAI HC/ML/ML 2/1. PCA.ipynb
blackbolt/data/ML TS XAI HC/ML/ML 2/10. CNN.ipynb
blackbolt/data/ML TS XAI HC/ML/ML 2/11. HMM.ipynb
blackbolt/data/ML TS XAI HC/ML/ML 2/2. KNN.ipynb
blackbolt/data/ML TS XAI HC/ML/ML 2/3. LDA.ipynb
blackbolt/data/ML TS XAI HC/ML/ML 2/4. Linear Regression.ipynb
blackbolt/data/ML TS XAI HC/ML/ML 2/5. Logistic Regression.ipynb
blackbolt/data/ML TS XAI HC/ML/ML 2/6. Naive Bayes (Titanic).ipynb
blackbolt/data/ML TS XAI HC/ML/ML 2/6. Naive Bayes (Wine).ipynb
blackbolt/data/ML TS XAI HC/ML/ML 2/7. SVM Linear.ipynb
blackbolt/data/ML TS XAI HC/ML/ML 2/8. SVM Non-Linear.ipynb
blackbolt-2.0.0.dist-info/licenses/LICENSE.txt
blackbolt-2.0.0.dist-info/METADATA
blackbolt-2.0.0.dist-info/WHEEL
blackbolt-2.0.0.dist-info/top_level.txt
blackbolt-2.0.0.dist-info/RECORD
